napari_deeplabcut/__init__.py
napari_deeplabcut/_reader.py
napari_deeplabcut/_version.py
napari_deeplabcut/_widgets.py
napari_deeplabcut/_writer.py
napari_deeplabcut/keypoints.py
napari_deeplabcut/misc.py
napari_deeplabcut/napari.yaml
napari_deeplabcut/_tests/__init__.py
napari_deeplabcut/_tests/conftest.py
napari_deeplabcut/_tests/test_keypoints.py
napari_deeplabcut/_tests/test_misc.py
napari_deeplabcut/_tests/test_reader.py
napari_deeplabcut/_tests/test_widgets.py
napari_deeplabcut/assets/napari_shortcuts.svg
napari_deeplabcut/assets/superanimal_quadruped.jpg
napari_deeplabcut/assets/superanimal_quadruped.json
napari_deeplabcut/assets/superanimal_topviewmouse.jpg
napari_deeplabcut/assets/superanimal_topviewmouse.json
napari_deeplabcut/assets/black/Back.png
napari_deeplabcut/assets/black/Customize.png
napari_deeplabcut/assets/black/Forward.png
napari_deeplabcut/assets/black/Home.png
napari_deeplabcut/assets/black/Pan.png
napari_deeplabcut/assets/black/Pan_checked.png
napari_deeplabcut/assets/black/Save.png
napari_deeplabcut/assets/black/Subplots.png
napari_deeplabcut/assets/black/Zoom.png
napari_deeplabcut/assets/black/Zoom_checked.png
napari_deeplabcut/assets/white/Back.png
napari_deeplabcut/assets/white/Customize.png
napari_deeplabcut/assets/white/Forward.png
napari_deeplabcut/assets/white/Home.png
napari_deeplabcut/assets/white/Pan.png
napari_deeplabcut/assets/white/Pan_checked.png
napari_deeplabcut/assets/white/Save.png
napari_deeplabcut/assets/white/Subplots.png
napari_deeplabcut/assets/white/Zoom.png
napari_deeplabcut/assets/white/Zoom_checked.png
napari_deeplabcut/styles/dark.mplstyle
napari_deeplabcut/styles/light.mplstyle
napari_deeplabcut-0.2.1.7.dist-info/LICENSE
napari_deeplabcut-0.2.1.7.dist-info/METADATA
napari_deeplabcut-0.2.1.7.dist-info/WHEEL
napari_deeplabcut-0.2.1.7.dist-info/entry_points.txt
napari_deeplabcut-0.2.1.7.dist-info/top_level.txt
napari_deeplabcut-0.2.1.7.dist-info/RECORD
