Metadata-Version: 2.1
Name: napari-deeplabcut
Version: 0.2.1.7
Summary: napari + DeepLabCut annotation tool
Home-page: https://github.com/DeepLabCut/napari-deeplabcut
Author: Team DeepLabCut, Lead by Jessy Lauer
Author-email: admin@deeplabcut.org
License: BSD-3-Clause
Project-URL: Bug Tracker, https://github.com/DeepLabCut/napari-deeplabcut/issues
Project-URL: Documentation, https://github.com/DeepLabCut/napari-deeplabcut#README.md
Project-URL: Source Code, https://github.com/DeepLabCut/napari-deeplabcut
Project-URL: User Support, https://github.com/DeepLabCut/napari-deeplabcut/issues
Classifier: Development Status :: 2 - Pre-Alpha
Classifier: Framework :: napari
Classifier: Intended Audience :: Developers
Classifier: License :: OSI Approved :: BSD License
Classifier: Operating System :: OS Independent
Classifier: Programming Language :: Python :: 3
Classifier: Programming Language :: Python :: 3 :: Only
Classifier: Programming Language :: Python :: 3.9
Classifier: Programming Language :: Python :: 3.10
Classifier: Topic :: Scientific/Engineering :: Artificial Intelligence
Classifier: Topic :: Scientific/Engineering :: Image Processing
Classifier: Topic :: Scientific/Engineering :: Visualization
Requires-Python: >=3.9
License-File: LICENSE
Requires-Dist: dask-image
Requires-Dist: matplotlib >=3.3
Requires-Dist: napari ==0.4.18
Requires-Dist: natsort
Requires-Dist: numpy
Requires-Dist: opencv-python-headless
Requires-Dist: pandas
Requires-Dist: pyyaml
Requires-Dist: qtpy >=2.4
Requires-Dist: scikit-image
Requires-Dist: scipy
Requires-Dist: tables
Provides-Extra: testing
Requires-Dist: pyside6 ==6.4.2 ; extra == 'testing'
Requires-Dist: pytest ; extra == 'testing'
Requires-Dist: pytest-cov ; extra == 'testing'
Requires-Dist: pytest-qt ; extra == 'testing'
Requires-Dist: tox ; extra == 'testing'
